{"architectures":[{"radioMaxRevisit":0.0,"reflMaxRevisitL":0.0,"avgRevisit":0.0,"maxRevisitP":0.0,"allCoverage":0.0,"reflAvgRevisitP":0.0,"maxRevisitL":0.0,"reflAvgRevisitL":0.0,"avgRevisitP":0.0,"allMaxRevisit":0.0,"avgRevisitL":0.0,"allAvgRevisit":0.0,"cost":368.4143029584767,"repeatCycle":7,"radioAvgRevisit":0.0,"combReflMaxRevisit":0.0,"reflCoverageL":0.0,"combReflCoverage":0.0,"reflCoverageP":0.0,"radioCoverage":0.0,"percentCoverage":0.0,"name":"LEO-502.5-89, repeat cycle of 7 days, 1 planes, 3 satellites per plane, radar satellites only","maxRevisit":0.0,"combReflAvgRevisit":0.0,"reflMaxRevisitP":0.0}]}